inflect/__init__.py
inflect/py.typed
inflect/compat/__init__.py
inflect/compat/py38.py
inflect-7.4.0.dist-info/LICENSE
inflect-7.4.0.dist-info/METADATA
inflect-7.4.0.dist-info/WHEEL
inflect-7.4.0.dist-info/top_level.txt
inflect-7.4.0.dist-info/RECORD
